securespeak/__init__.py
securespeak/client.py
securespeakai_sdk-1.0.1.dist-info/METADATA
securespeakai_sdk-1.0.1.dist-info/WHEEL
securespeakai_sdk-1.0.1.dist-info/top_level.txt
securespeakai_sdk-1.0.1.dist-info/RECORD
