Metadata-Version: 2.1
Name: securespeakai-sdk
Version: 1.0.1
Summary: SecureSpeakAI Python SDK for deepfake detection with comprehensive API support
Home-page: https://securespeakai.com
Author: SecureSpeakAI
Author-email: nsharma@securespeakai.com
Project-URL: Documentation, https://securespeakai.com/docs
Project-URL: Homepage, https://securespeakai.com
Project-URL: Support, https://securespeakai.com/support
Keywords: deepfake detection,audio analysis,AI,machine learning,api,sdk
Classifier: Programming Language :: Python :: 3
Classifier: Programming Language :: Python :: 3.7
Classifier: Programming Language :: Python :: 3.8
Classifier: Programming Language :: Python :: 3.9
Classifier: Programming Language :: Python :: 3.10
Classifier: Programming Language :: Python :: 3.11
Classifier: License :: OSI Approved :: MIT License
Classifier: Operating System :: OS Independent
Classifier: Development Status :: 4 - Beta
Classifier: Intended Audience :: Developers
Classifier: Topic :: Software Development :: Libraries :: Python Modules
Classifier: Topic :: Scientific/Engineering :: Artificial Intelligence
Classifier: Topic :: Multimedia :: Sound/Audio :: Analysis
Requires-Python: >=3.7
Requires-Dist: requests >=2.25.0
Requires-Dist: websocket-client >=1.2.0
Requires-Dist: typing-extensions >=4.0.0
Requires-Dist: pyaudio >=0.2.11
